hw_2/__init__.py
hw_2/generate_table_artifact.py
hw_2/latex_table.py
liub_itmo_sem1_python_hw-0.2.3.dist-info/METADATA
liub_itmo_sem1_python_hw-0.2.3.dist-info/WHEEL
liub_itmo_sem1_python_hw-0.2.3.dist-info/top_level.txt
liub_itmo_sem1_python_hw-0.2.3.dist-info/RECORD
