Metadata-Version: 2.4
Name: liub-itmo-sem1-python-hw
Version: 0.2.3
Summary: ITMO Python Liubinetskii Homeworks
Requires-Python: >=3.10
